xfyunsdkspark/__init__.py
xfyunsdkspark/agent_client.py
xfyunsdkspark/ai_ppt.py
xfyunsdkspark/aiui_knowledge_client.py
xfyunsdkspark/oral_chat_client.py
xfyunsdkspark/oral_client.py
xfyunsdkspark/resume_generate_client.py
xfyunsdkspark/spark_iat_client.py
xfyunsdkspark/voice_clone.py
xfyunsdkspark/voice_train.py
xfyunsdkspark-0.0.3.dist-info/LICENSE
xfyunsdkspark-0.0.3.dist-info/METADATA
xfyunsdkspark-0.0.3.dist-info/WHEEL
xfyunsdkspark-0.0.3.dist-info/top_level.txt
xfyunsdkspark-0.0.3.dist-info/RECORD
